prewl/__init__.py
prewl/model.py
prewl/prompts.py
prewl/endpoints/__init__.py
prewl/endpoints/base.py
prewl/endpoints/gpt3.py
prewl/endpoints/hf.py
prewl/endpoints/manual.py
prewl-0.0.4.dist-info/LICENSE
prewl-0.0.4.dist-info/METADATA
prewl-0.0.4.dist-info/WHEEL
prewl-0.0.4.dist-info/top_level.txt
prewl-0.0.4.dist-info/RECORD
