Metadata-Version: 2.1
Name: prewl
Version: 0.0.4
Summary: General library wrapping and calling LLMs for prompt engineering.
Home-page: https://github.com/queens-supercluster/prewl
Author: Erin Atacan and Christian Muise
Author-email: christian.muise@queensu.ca
License: MIT
Classifier: Programming Language :: Python :: 3
Classifier: License :: OSI Approved :: MIT License
Classifier: Operating System :: POSIX :: Linux
Requires-Python: >=3.6
License-File: LICENSE
Requires-Dist: requests
